pyRDDLGym/__init__.py
pyRDDLGym/registration.py
pyRDDLGym/core/__init__.py
pyRDDLGym/core/builder.py
pyRDDLGym/core/client.py
pyRDDLGym/core/constraints.py
pyRDDLGym/core/env.py
pyRDDLGym/core/grounder.py
pyRDDLGym/core/intervals.py
pyRDDLGym/core/policy.py
pyRDDLGym/core/server.py
pyRDDLGym/core/simulator.py
pyRDDLGym/core/compiler/__init__.py
pyRDDLGym/core/compiler/initializer.py
pyRDDLGym/core/compiler/levels.py
pyRDDLGym/core/compiler/model.py
pyRDDLGym/core/compiler/tracer.py
pyRDDLGym/core/debug/__init__.py
pyRDDLGym/core/debug/decompiler.py
pyRDDLGym/core/debug/exception.py
pyRDDLGym/core/debug/logger.py
pyRDDLGym/core/parser/__init__.py
pyRDDLGym/core/parser/cpf.py
pyRDDLGym/core/parser/domain.py
pyRDDLGym/core/parser/expr.py
pyRDDLGym/core/parser/instance.py
pyRDDLGym/core/parser/nonfluents.py
pyRDDLGym/core/parser/parser.py
pyRDDLGym/core/parser/pvariable.py
pyRDDLGym/core/parser/rddl.py
pyRDDLGym/core/parser/reader.py
pyRDDLGym/core/parser/utils.py
pyRDDLGym/core/visualizer/__init__.py
pyRDDLGym/core/visualizer/chart.py
pyRDDLGym/core/visualizer/heatmap.py
pyRDDLGym/core/visualizer/movie.py
pyRDDLGym/core/visualizer/text.py
pyRDDLGym/core/visualizer/viz.py
pyRDDLGym/examples/__init__.py
pyRDDLGym/examples/run_build.py
pyRDDLGym/examples/run_ground.py
pyRDDLGym/examples/run_gym.py
pyRDDLGym/examples/run_gym2.py
pyRDDLGym/examples/run_intervals.py
pyRDDLGym/examples/run_server.py
pyrddlgym-2.6.dist-info/licenses/LICENSE
pyrddlgym-2.6.dist-info/METADATA
pyrddlgym-2.6.dist-info/WHEEL
pyrddlgym-2.6.dist-info/top_level.txt
pyrddlgym-2.6.dist-info/RECORD
